aida_utils/__init__.py
aida_utils/utils.py
aida_utils-0.1.1.dist-info/METADATA
aida_utils-0.1.1.dist-info/WHEEL
aida_utils-0.1.1.dist-info/RECORD
