Metadata-Version: 2.4
Name: aida-utils
Version: 0.1.1
Summary: Utils used at aida-lab
Author-email: Jan Aerts <jan.aerts@kuleuven.be>
License: MIT
Requires-Python: >=3.11
Requires-Dist: matplotlib
Requires-Dist: numpy>=2.3.0
Requires-Dist: scipy>=1.15.3
